{
    "Eval": [
        {
            "Checkbox": true,
            "Informativeness": 6,
            "Naturalness": 6,
            "Quality": 6,
            "Restriction": true
        },
        {
            "Checkbox": true,
            "Informativeness": 6,
            "Naturalness": 6,
            "Quality": 6,
            "Restriction": true
        },
        {
            "Checkbox": true,
            "Informativeness": 6,
            "Naturalness": 5,
            "Quality": 5,
            "Restriction": true
        }
    ],
    "Text": "노무현이 있는 정당은 민주당이다. 민주당의 본부는 부산광역시에 있다. ",
    "entities": {
        "노무현": {
            "ne_type": "PS_NAME",
            "type": [
                "http://dbpedia.org/ontology/Person",
                "http://dbpedia.org/ontology/Politician",
                "http://dbpedia.org/ontology/President",
                "http://dbpedia.org/ontology/Agent"
            ],
            "uri": "http://kbox.kaist.ac.kr/resource/노무현"
        },
        "민주당": {
            "ne_type": "OGG_POLITICS",
            "type": [
                "http://dbpedia.org/ontology/Organisation",
                "http://dbpedia.org/ontology/Agent",
                "http://dbpedia.org/ontology/PoliticalParty"
            ],
            "uri": "http://kbox.kaist.ac.kr/resource/민주당_(미국)"
        },
        "부산광역시": {
            "ne_type": "LCP_CITY",
            "type": [
                "http://dbpedia.org/ontology/City",
                "http://dbpedia.org/ontology/Location",
                "http://dbpedia.org/ontology/Settlement",
                "http://dbpedia.org/ontology/PopulatedPlace",
                "http://dbpedia.org/ontology/Place"
            ],
            "uri": "http://kbox.kaist.ac.kr/resource/부산광역시"
        }
    },
    "id": 3608,
    "pid": "114-28",
    "triple": [
        {
            "Rep": true,
            "o": "민주당",
            "p": "정당(party)",
            "s": "노무현"
        },
        {
            "Rep": false,
            "o": "민주당",
            "p": "정당(party)",
            "s": "부산광역시"
        },
        {
            "Rep": true,
            "o": "부산광역시",
            "p": "본부/본사(headquarter)",
            "s": "민주당"
        },
        {
            "Rep": false,
            "o": "노무현",
            "p": "지도자(leader)",
            "s": "민주당"
        }
    ]
}