{
    "Eval": [
        {
            "Checkbox": true,
            "Informativeness": 6,
            "Naturalness": 6,
            "Quality": 6,
            "Restriction": true
        },
        {
            "Checkbox": false,
            "Informativeness": 2,
            "Naturalness": 6,
            "Quality": 6,
            "Restriction": false
        },
        {
            "Checkbox": true,
            "Informativeness": 6,
            "Naturalness": 6,
            "Quality": 6,
            "Restriction": true
        }
    ],
    "Text": "교황의 국가는 프랑스이다. 교황은 십자군 전투에 참여했다.",
    "entities": {
        "교황": {
            "ne_type": "CV_POSITION",
            "type": [
                "http://dbpedia.org/ontology/Person",
                "http://dbpedia.org/ontology/ChristianBishop",
                "http://dbpedia.org/ontology/Agent",
                "http://dbpedia.org/ontology/Cleric"
            ],
            "uri": "http://kbox.kaist.ac.kr/resource/교황"
        },
        "교황_특사": {
            "ne_type": "CV_POSITION",
            "type": [
                "http://dbpedia.org/ontology/PersonFunction",
                "http://dbpedia.org/ontology/Profession"
            ],
            "uri": "http://kbox.kaist.ac.kr/resource/교황_특사"
        },
        "샤를_2세": {
            "ne_type": "PS_NAME",
            "type": [
                "http://dbpedia.org/ontology/Person",
                "http://dbpedia.org/ontology/Agent",
                "http://dbpedia.org/ontology/Noble"
            ],
            "uri": "http://kbox.kaist.ac.kr/resource/샤를_2세_(프로방스)"
        },
        "시칠리아": {
            "ne_type": "LCP_PROVINCE",
            "type": [
                "http://dbpedia.org/ontology/Region",
                "http://dbpedia.org/ontology/AdministrativeRegion",
                "http://dbpedia.org/ontology/PopulatedPlace",
                "http://dbpedia.org/ontology/EthnicGroup",
                "http://dbpedia.org/ontology/Place"
            ],
            "uri": "http://kbox.kaist.ac.kr/resource/시칠리아"
        },
        "십자군": {
            "ne_type": "OGG_MILITARY",
            "type": [
                "http://dbpedia.org/ontology/MilitaryConflict",
                "http://dbpedia.org/ontology/Event",
                "http://dbpedia.org/ontology/SocietalEvent"
            ],
            "uri": "http://kbox.kaist.ac.kr/resource/십자군"
        },
        "앙주": {
            "ne_type": "LCP_PROVINCE",
            "type": [
                "http://dbpedia.org/ontology/Settlement",
                "http://dbpedia.org/ontology/PopulatedPlace",
                "http://dbpedia.org/ontology/Place"
            ],
            "uri": "http://kbox.kaist.ac.kr/resource/앙주"
        },
        "카를로_1세": {
            "ne_type": "PS_NAME",
            "type": [
                "http://dbpedia.org/ontology/Person",
                "http://dbpedia.org/ontology/Royalty",
                "http://dbpedia.org/ontology/BritishRoyalty",
                "http://dbpedia.org/ontology/Agent"
            ],
            "uri": "http://kbox.kaist.ac.kr/resource/카를로_1세"
        },
        "파리": {
            "ne_type": "LCP_CAPITALCITY",
            "type": [
                "http://dbpedia.org/ontology/Location",
                "http://dbpedia.org/ontology/Settlement",
                "http://dbpedia.org/ontology/PopulatedPlace",
                "http://dbpedia.org/ontology/Place"
            ],
            "uri": "http://kbox.kaist.ac.kr/resource/파리_(프랑스)"
        },
        "프랑스": {
            "ne_type": "LCP_COUNTRY",
            "type": [
                "http://dbpedia.org/ontology/Settlement",
                "http://dbpedia.org/ontology/PopulatedPlace",
                "http://dbpedia.org/ontology/Place",
                "http://dbpedia.org/ontology/Country"
            ],
            "uri": "http://kbox.kaist.ac.kr/resource/프랑스"
        }
    },
    "id": 1127,
    "pid": "13-4",
    "triple": [
        {
            "Rep": false,
            "o": "프랑스",
            "p": "국가(country)",
            "s": "파리"
        },
        {
            "Rep": false,
            "o": "교황",
            "p": "직함/포지션(position)",
            "s": "교황_특사"
        },
        {
            "Rep": true,
            "o": "프랑스",
            "p": "국가(country)",
            "s": "교황"
        },
        {
            "Rep": false,
            "o": "교황",
            "p": "직함/포지션(position)",
            "s": "십자군"
        },
        {
            "Rep": false,
            "o": "프랑스",
            "p": "국가(country)",
            "s": "교황_특사"
        },
        {
            "Rep": false,
            "o": "교황_특사",
            "p": "수도(capital)",
            "s": "프랑스"
        },
        {
            "Rep": false,
            "o": "시칠리아",
            "p": "지역/분양(region)",
            "s": "앙주"
        },
        {
            "Rep": true,
            "o": "십자군",
            "p": "전투(battle)",
            "s": "교황"
        },
        {
            "Rep": false,
            "o": "카를로_1세",
            "p": "리더이름(leaderName)",
            "s": "앙주"
        },
        {
            "Rep": false,
            "o": "교황",
            "p": "직업(occupation)",
            "s": "교황_특사"
        },
        {
            "Rep": false,
            "o": "샤를_2세",
            "p": "리더이름(leaderName)",
            "s": "앙주"
        }
    ]
}