{
    "Eval": [
        {
            "Checkbox": true,
            "Informativeness": 6,
            "Naturalness": 6,
            "Quality": 6,
            "Restriction": true
        },
        {
            "Checkbox": true,
            "Informativeness": 6,
            "Naturalness": 6,
            "Quality": 6,
            "Restriction": true
        },
        {
            "Checkbox": true,
            "Informativeness": 6,
            "Naturalness": 6,
            "Quality": 6,
            "Restriction": true
        }
    ],
    "Text": "셀림 1세는 오스만 제국의 리더였다. 그는 십자군 전투를 지휘했다.",
    "entities": {
        "교황_레오_10세": {
            "ne_type": "PS_NAME",
            "type": [
                "http://dbpedia.org/ontology/Person",
                "http://dbpedia.org/ontology/Pope",
                "http://dbpedia.org/ontology/ChristianBishop",
                "http://dbpedia.org/ontology/Cleric",
                "http://dbpedia.org/ontology/Agent"
            ],
            "uri": "http://kbox.kaist.ac.kr/resource/교황_레오_10세"
        },
        "셀림_1세": {
            "ne_type": "PS_NAME",
            "type": [
                "http://dbpedia.org/ontology/Person",
                "http://dbpedia.org/ontology/Royalty",
                "http://dbpedia.org/ontology/Monarch",
                "http://dbpedia.org/ontology/BritishRoyalty",
                "http://dbpedia.org/ontology/Agent"
            ],
            "uri": "http://kbox.kaist.ac.kr/resource/셀림_1세"
        },
        "스페인": {
            "ne_type": "LCP_COUNTRY",
            "type": [
                "http://dbpedia.org/ontology/Settlement",
                "http://dbpedia.org/ontology/PopulatedPlace",
                "http://dbpedia.org/ontology/Place",
                "http://dbpedia.org/ontology/Country"
            ],
            "uri": "http://kbox.kaist.ac.kr/resource/스페인"
        },
        "신성_로마_제국": {
            "ne_type": "LCP_COUNTRY",
            "type": [
                "http://dbpedia.org/ontology/PopulatedPlace",
                "http://dbpedia.org/ontology/Place",
                "http://dbpedia.org/ontology/Country"
            ],
            "uri": "http://kbox.kaist.ac.kr/resource/신성_로마_제국"
        },
        "십자군": {
            "ne_type": "OGG_MILITARY",
            "type": [
                "http://dbpedia.org/ontology/MilitaryConflict",
                "http://dbpedia.org/ontology/Event",
                "http://dbpedia.org/ontology/SocietalEvent"
            ],
            "uri": "http://kbox.kaist.ac.kr/resource/십자군"
        },
        "오스만_제국": {
            "ne_type": "LCP_COUNTRY",
            "type": [
                "http://dbpedia.org/ontology/Organisation",
                "http://dbpedia.org/ontology/PopulatedPlace",
                "http://dbpedia.org/ontology/Place",
                "http://dbpedia.org/ontology/Agent",
                "http://dbpedia.org/ontology/University",
                "http://dbpedia.org/ontology/EducationalInstitution",
                "http://dbpedia.org/ontology/Country"
            ],
            "uri": "http://kbox.kaist.ac.kr/resource/오스만_제국"
        },
        "잉글랜드": {
            "ne_type": "LCP_COUNTRY",
            "type": [
                "http://dbpedia.org/ontology/Settlement",
                "http://dbpedia.org/ontology/PopulatedPlace",
                "http://dbpedia.org/ontology/Place",
                "http://dbpedia.org/ontology/Country"
            ],
            "uri": "http://kbox.kaist.ac.kr/resource/잉글랜드"
        },
        "토머스_울지": {
            "ne_type": "PS_NAME",
            "type": [
                "http://dbpedia.org/ontology/Person",
                "http://dbpedia.org/ontology/Agent",
                "http://dbpedia.org/ontology/OfficeHolder"
            ],
            "uri": "http://kbox.kaist.ac.kr/resource/토머스_울지"
        },
        "포르투갈": {
            "ne_type": "LCP_COUNTRY",
            "type": [
                "http://dbpedia.org/ontology/Settlement",
                "http://dbpedia.org/ontology/PopulatedPlace",
                "http://dbpedia.org/ontology/Place",
                "http://dbpedia.org/ontology/Country"
            ],
            "uri": "http://kbox.kaist.ac.kr/resource/포르투갈"
        },
        "프랑스": {
            "ne_type": "LCP_COUNTRY",
            "type": [
                "http://dbpedia.org/ontology/Settlement",
                "http://dbpedia.org/ontology/PopulatedPlace",
                "http://dbpedia.org/ontology/Place",
                "http://dbpedia.org/ontology/Country"
            ],
            "uri": "http://kbox.kaist.ac.kr/resource/프랑스"
        }
    },
    "id": 1811,
    "pid": "42-14",
    "triple": [
        {
            "Rep": false,
            "o": "프랑스",
            "p": "국가(country)",
            "s": "잉글랜드"
        },
        {
            "Rep": true,
            "o": "셀림_1세",
            "p": "리더이름(leaderName)",
            "s": "오스만_제국"
        },
        {
            "Rep": false,
            "o": "포르투갈",
            "p": "국가(country)",
            "s": "잉글랜드"
        },
        {
            "Rep": false,
            "o": "스페인",
            "p": "국가(country)",
            "s": "잉글랜드"
        },
        {
            "Rep": false,
            "o": "스페인",
            "p": "국가(country)",
            "s": "포르투갈"
        },
        {
            "Rep": false,
            "o": "십자군",
            "p": "수도(capital)",
            "s": "오스만_제국"
        },
        {
            "Rep": false,
            "o": "토머스_울지",
            "p": "리더이름(leaderName)",
            "s": "신성_로마_제국"
        },
        {
            "Rep": false,
            "o": "교황_레오_10세",
            "p": "리더이름(leaderName)",
            "s": "오스만_제국"
        },
        {
            "Rep": true,
            "o": "셀림_1세",
            "p": "지휘관(commander)",
            "s": "십자군"
        },
        {
            "Rep": false,
            "o": "십자군",
            "p": "수도(capital)",
            "s": "프랑스"
        },
        {
            "Rep": false,
            "o": "교황_레오_10세",
            "p": "리더이름(leaderName)",
            "s": "신성_로마_제국"
        },
        {
            "Rep": false,
            "o": "교황_레오_10세",
            "p": "지휘관(commander)",
            "s": "십자군"
        },
        {
            "Rep": false,
            "o": "십자군",
            "p": "수도(capital)",
            "s": "신성_로마_제국"
        },
        {
            "Rep": false,
            "o": "포르투갈",
            "p": "국가(country)",
            "s": "스페인"
        }
    ]
}