{
    "Eval": [
        {
            "Checkbox": false,
            "Informativeness": 4,
            "Naturalness": 4,
            "Quality": 5,
            "Restriction": true
        },
        {
            "Checkbox": false,
            "Informativeness": 1,
            "Naturalness": 2,
            "Quality": 5,
            "Restriction": false
        },
        {
            "Checkbox": false,
            "Informativeness": 2,
            "Naturalness": 5,
            "Quality": 5,
            "Restriction": true
        }
    ],
    "Text": "십자군의 지휘관은 카를로 1세이다. 카를로 1세는 로마의 황제이다. 카를로 1세는 의원직을 했다.",
    "entities": {
        "교황_마르티노_4세": {
            "ne_type": "PS_NAME",
            "type": [
                "http://dbpedia.org/ontology/Person",
                "http://dbpedia.org/ontology/Pope",
                "http://dbpedia.org/ontology/ChristianBishop",
                "http://dbpedia.org/ontology/Cleric",
                "http://dbpedia.org/ontology/Agent"
            ],
            "uri": "http://kbox.kaist.ac.kr/resource/교황_마르티노_4세"
        },
        "라틴_제국": {
            "ne_type": "LCP_COUNTRY",
            "type": [
                "http://dbpedia.org/ontology/Location",
                "http://dbpedia.org/ontology/PopulatedPlace",
                "http://dbpedia.org/ontology/Place",
                "http://dbpedia.org/ontology/Country"
            ],
            "uri": "http://kbox.kaist.ac.kr/resource/라틴_제국"
        },
        "로마": {
            "ne_type": "LCP_COUNTRY",
            "type": [
                "http://dbpedia.org/ontology/Location",
                "http://dbpedia.org/ontology/Settlement",
                "http://dbpedia.org/ontology/PopulatedPlace",
                "http://dbpedia.org/ontology/Place"
            ],
            "uri": "http://kbox.kaist.ac.kr/resource/로마"
        },
        "십자군": {
            "ne_type": "OGG_MILITARY",
            "type": [
                "http://dbpedia.org/ontology/MilitaryConflict",
                "http://dbpedia.org/ontology/Event",
                "http://dbpedia.org/ontology/SocietalEvent"
            ],
            "uri": "http://kbox.kaist.ac.kr/resource/십자군"
        },
        "의원": {
            "ne_type": "CV_POSITION",
            "type": [
                "http://dbpedia.org/ontology/PersonFunction",
                "http://dbpedia.org/ontology/Profession"
            ],
            "uri": "http://kbox.kaist.ac.kr/resource/의원"
        },
        "조반니_디_코시모_데_메디치": {
            "ne_type": "PS_NAME",
            "type": [
                "http://dbpedia.org/ontology/Person",
                "http://dbpedia.org/ontology/Agent",
                "http://dbpedia.org/ontology/Noble"
            ],
            "uri": "http://kbox.kaist.ac.kr/resource/조반니_디_코시모_데_메디치"
        },
        "카를로_1세": {
            "ne_type": "PS_NAME",
            "type": [
                "http://dbpedia.org/ontology/Person",
                "http://dbpedia.org/ontology/Royalty",
                "http://dbpedia.org/ontology/BritishRoyalty",
                "http://dbpedia.org/ontology/Agent"
            ],
            "uri": "http://kbox.kaist.ac.kr/resource/카를로_1세"
        }
    },
    "id": 107,
    "pid": "13-7",
    "triple": [
        {
            "Rep": false,
            "o": "카를로_1세",
            "p": "리더이름(leaderName)",
            "s": "라틴_제국"
        },
        {
            "Rep": true,
            "o": "카를로_1세",
            "p": "지휘관(commander)",
            "s": "십자군"
        },
        {
            "Rep": false,
            "o": "십자군",
            "p": "전투(battle)",
            "s": "교황_마르티노_4세"
        },
        {
            "Rep": true,
            "o": "의원",
            "p": "직함/포지션(position)",
            "s": "카를로_1세"
        },
        {
            "Rep": false,
            "o": "조반니_디_코시모_데_메디치",
            "p": "지도자(leader)",
            "s": "의원"
        },
        {
            "Rep": true,
            "o": "카를로_1세",
            "p": "리더이름(leaderName)",
            "s": "로마"
        },
        {
            "Rep": false,
            "o": "십자군",
            "p": "전투(battle)",
            "s": "카를로_1세"
        }
    ]
}