{
    "Eval": [
        {
            "Checkbox": true,
            "Informativeness": 6,
            "Naturalness": 5,
            "Quality": 5,
            "Restriction": false
        },
        {
            "Checkbox": true,
            "Informativeness": 6,
            "Naturalness": 4,
            "Quality": 6,
            "Restriction": true
        },
        {
            "Checkbox": true,
            "Informativeness": 6,
            "Naturalness": 6,
            "Quality": 6,
            "Restriction": false
        }
    ],
    "Text": "막스 보른은 독일 국적이다. 그는 독일의 지도자이다.",
    "entities": {
        "독일": {
            "ne_type": "LCP_COUNTRY",
            "type": [
                "http://dbpedia.org/ontology/Settlement",
                "http://dbpedia.org/ontology/PopulatedPlace",
                "http://dbpedia.org/ontology/Place",
                "http://dbpedia.org/ontology/Country"
            ],
            "uri": "http://kbox.kaist.ac.kr/resource/독일"
        },
        "독일어": {
            "ne_type": "CV_LANGUAGE",
            "type": [
                "http://dbpedia.org/ontology/Language"
            ],
            "uri": "http://kbox.kaist.ac.kr/resource/독일어"
        },
        "막스_보른": {
            "ne_type": "PS_NAME",
            "type": [
                "http://dbpedia.org/ontology/Person",
                "http://dbpedia.org/ontology/Scientist",
                "http://dbpedia.org/ontology/Agent"
            ],
            "uri": "http://kbox.kaist.ac.kr/resource/막스_보른"
        },
        "영어": {
            "ne_type": "CV_LANGUAGE",
            "type": [
                "http://dbpedia.org/ontology/Language"
            ],
            "uri": "http://kbox.kaist.ac.kr/resource/영어"
        }
    },
    "id": 170,
    "pid": "173-4",
    "triple": [
        {
            "Rep": true,
            "o": "독일",
            "p": "국적(nationality)",
            "s": "막스_보른"
        },
        {
            "Rep": false,
            "o": "영어",
            "p": "계통(languageFamily)",
            "s": "독일어"
        },
        {
            "Rep": true,
            "o": "막스_보른",
            "p": "지도자(leader)",
            "s": "독일"
        },
        {
            "Rep": false,
            "o": "독일어",
            "p": "계통(languageFamily)",
            "s": "영어"
        }
    ]
}