{
    "Eval": [
        {
            "Checkbox": true,
            "Informativeness": 2,
            "Naturalness": 3,
            "Quality": 1,
            "Restriction": true
        },
        {
            "Checkbox": true,
            "Informativeness": 3,
            "Naturalness": 3,
            "Quality": 3,
            "Restriction": true
        },
        {
            "Checkbox": true,
            "Informativeness": 6,
            "Naturalness": 6,
            "Quality": 6,
            "Restriction": true
        }
    ],
    "Text": "위안스카이는 청나라의 리더이다. 그는 붉은 군대를 지휘했다. ",
    "entities": {
        "붉은_군대": {
            "ne_type": "OGG_MILITARY",
            "type": [
                "http://dbpedia.org/ontology/MilitaryUnit",
                "http://dbpedia.org/ontology/Organisation",
                "http://dbpedia.org/ontology/Agent"
            ],
            "uri": "http://kbox.kaist.ac.kr/resource/붉은_군대"
        },
        "사마의": {
            "ne_type": "PS_NAME",
            "type": [
                "http://dbpedia.org/ontology/Person",
                "http://dbpedia.org/ontology/Agent"
            ],
            "uri": "http://kbox.kaist.ac.kr/resource/사마의"
        },
        "위안스카이": {
            "ne_type": "PS_NAME",
            "type": [
                "http://dbpedia.org/ontology/Person",
                "http://dbpedia.org/ontology/Politician",
                "http://dbpedia.org/ontology/President",
                "http://dbpedia.org/ontology/Governor",
                "http://dbpedia.org/ontology/Agent",
                "http://dbpedia.org/ontology/OfficeHolder"
            ],
            "uri": "http://kbox.kaist.ac.kr/resource/위안스카이"
        },
        "청나라": {
            "ne_type": "LCP_COUNTRY",
            "type": [
                "http://dbpedia.org/ontology/Location",
                "http://dbpedia.org/ontology/PopulatedPlace",
                "http://dbpedia.org/ontology/Place",
                "http://dbpedia.org/ontology/Country"
            ],
            "uri": "http://kbox.kaist.ac.kr/resource/청나라"
        }
    },
    "id": 265,
    "pid": "195-67",
    "triple": [
        {
            "Rep": true,
            "o": "위안스카이",
            "p": "리더이름(leaderName)",
            "s": "청나라"
        },
        {
            "Rep": false,
            "o": "사마의",
            "p": "리더이름(leaderName)",
            "s": "청나라"
        },
        {
            "Rep": true,
            "o": "위안스카이",
            "p": "지휘관(commander)",
            "s": "붉은_군대"
        },
        {
            "Rep": false,
            "o": "사마의",
            "p": "지휘관(commander)",
            "s": "붉은_군대"
        }
    ]
}