{
    "Eval": [
        {
            "Checkbox": true,
            "Informativeness": 2,
            "Naturalness": 2,
            "Quality": 2,
            "Restriction": true
        },
        {
            "Checkbox": false,
            "Informativeness": 2,
            "Naturalness": 3,
            "Quality": 4,
            "Restriction": true
        },
        {
            "Checkbox": true,
            "Informativeness": 4,
            "Naturalness": 3,
            "Quality": 3,
            "Restriction": true
        }
    ],
    "Text": "교황 그레고리오 16세의 직함은 교황이다. 독일의 국가는 벨기에이다. 벨기에는 독일의 국가다.",
    "entities": {
        "교황": {
            "ne_type": "CV_POSITION",
            "type": [
                "http://dbpedia.org/ontology/Person",
                "http://dbpedia.org/ontology/ChristianBishop",
                "http://dbpedia.org/ontology/Agent",
                "http://dbpedia.org/ontology/Cleric"
            ],
            "uri": "http://kbox.kaist.ac.kr/resource/교황"
        },
        "교황_그레고리오_16세": {
            "ne_type": "PS_NAME",
            "type": [
                "http://dbpedia.org/ontology/Person",
                "http://dbpedia.org/ontology/Pope",
                "http://dbpedia.org/ontology/ChristianBishop",
                "http://dbpedia.org/ontology/Cleric",
                "http://dbpedia.org/ontology/Agent"
            ],
            "uri": "http://kbox.kaist.ac.kr/resource/교황_그레고리오_16세"
        },
        "독일": {
            "ne_type": "LCP_COUNTRY",
            "type": [
                "http://dbpedia.org/ontology/Settlement",
                "http://dbpedia.org/ontology/PopulatedPlace",
                "http://dbpedia.org/ontology/Place",
                "http://dbpedia.org/ontology/Country"
            ],
            "uri": "http://kbox.kaist.ac.kr/resource/독일"
        },
        "벨기에": {
            "ne_type": "LCP_COUNTRY",
            "type": [
                "http://dbpedia.org/ontology/Settlement",
                "http://dbpedia.org/ontology/PopulatedPlace",
                "http://dbpedia.org/ontology/Place",
                "http://dbpedia.org/ontology/Country"
            ],
            "uri": "http://kbox.kaist.ac.kr/resource/벨기에"
        }
    },
    "id": 601,
    "pid": "78-12",
    "triple": [
        {
            "Rep": true,
            "o": "교황",
            "p": "직함/포지션(position)",
            "s": "교황_그레고리오_16세"
        },
        {
            "Rep": true,
            "o": "벨기에",
            "p": "국가(country)",
            "s": "독일"
        },
        {
            "Rep": true,
            "o": "독일",
            "p": "국가(country)",
            "s": "벨기에"
        },
        {
            "Rep": false,
            "o": "교황_그레고리오_16세",
            "p": "계승자/후임(successor)",
            "s": "교황"
        }
    ]
}